{
    "playerResults": {
        "geoff hodgson": {
            "totalAgg": 876,
            "totalAggAgainst": 793,
            "availableAgg": 1029,
            "availablePairsAgg": 0,
            "availableHomeAgg": 546,
            "availableAwayAgg": 483,
            "availablePairsHomeAgg": 0,
            "availablePairsAwayAgg": 0,
            "totalPairsAgg": 0,
            "totalPairsAggAgainst": 0,
            "totalHomeAgg": 485,
            "totalHomeAggAgainst": 400,
            "totalPairsHomeAgg": 0,
            "totalPairsHomeAggAgainst": 0,
            "totalAwayAgg": 391,
            "totalAwayAggAgainst": 393,
            "totalPairsAwayAgg": 0,
            "totalPairsAwayAggAgainst": 0,
            "homeWins": 17,
            "homeLosses": 9,
            "awayWins": 11,
            "awayLosses": 12,
            "cupWins": 0,
            "cupLosses": 0,
            "pairWins": 0,
            "pairLosses": 0,
            "pairHomeWins": 0,
            "pairHomeLosses": 0,
            "pairAwayWins": 0,
            "pairAwayLosses": 0,
            "pairCupWins": 0,
            "pairCupLosses": 0,
            "totalGamesPlayed": 49,
            "results": [
                "geoff hodgson 11 - 21 lorna mcquade",
                "geoff hodgson 21 - 4 harold watson",
                "geoff hodgson 21 - 13 val mottershead",
                "geoff hodgson 21 - 11 doreen stephenson",
                "geoff hodgson 18 - 21 gordon dick",
                "geoff hodgson 15 - 21 chris gardner",
                "geoff hodgson 21 - 7 dorothy jackson",
                "geoff hodgson 21 - 6 linda utley",
                "geoff hodgson 21 - 18 brenda evans",
                "geoff hodgson 15 - 21 charles holden",
                "geoff hodgson 16 - 21 jack beck",
                "geoff hodgson 21 - 13 jim dobson",
                "geoff hodgson 21 - 11 alan parkinson",
                "geoff hodgson 21 - 19 terry powell",
                "geoff hodgson 21 - 14 mavis harwood",
                "geoff hodgson 13 - 21 linda utley",
                "geoff hodgson 21 - 15 ernest tiffany",
                "geoff hodgson 21 - 13 derek dillon",
                "geoff hodgson 14 - 21 david crosland",
                "geoff hodgson 10 - 21 marion walton",
                "geoff hodgson 21 - 17 david lord",
                "geoff hodgson 21 - 6 ronnie spence",
                "geoff hodgson 18 - 21 john stevenson",
                "geoff hodgson 9 - 21 brian hemingway",
                "geoff hodgson 16 - 21 allan johnson",
                "geoff hodgson 21 - 10 george auckland",
                "geoff hodgson 21 - 15 audrey healey",
                "geoff hodgson 14 - 21 john preistley",
                "geoff hodgson 12 - 21 roy wood",
                "geoff hodgson 8 - 21 pat jagger",
                "geoff hodgson 21 - 17 bernard cahill",
                "geoff hodgson 21 - 14 trevor smith",
                "geoff hodgson 9 - 21 michael sansome",
                "geoff hodgson 18 - 21 marlene hughes",
                "geoff hodgson 21 - 20 wendy shimbles (a)",
                "geoff hodgson 21 - 12 lynn seddon",
                "geoff hodgson 21 - 13 keith woodhead",
                "geoff hodgson 15 - 21 john shoesmith",
                "geoff hodgson 20 - 21 bernard palmer",
                "geoff hodgson 21 - 12 chris moore",
                "geoff hodgson 21 - 10 michael holleran",
                "geoff hodgson 17 - 21 kenneth smith",
                "geoff hodgson 21 - 15 victor riley",
                "geoff hodgson 21 - 13 norman lickley",
                "geoff hodgson 21 - 4 alan holdsworth",
                "geoff hodgson 21 - 10 janet inness",
                "geoff hodgson 10 - 21 john ramsey",
                "geoff hodgson 21 - 20 keith worrall",
                "geoff hodgson 10 - 21 richard hunter"
            ],
            "airewharfe monday": {
                "games": 0,
                "wins": 0,
                "aggDiff": 0
            },
            "airewharfe monday (b)": {
                "games": 16,
                "wins": 10,
                "aggDiff": 56
            },
            "mirfield": {
                "games": 0,
                "wins": 0,
                "aggDiff": 0
            },
            "mirfield (b)": {
                "games": 0,
                "wins": 0,
                "aggDiff": 0
            },
            "bradford vets": {
                "games": 0,
                "wins": 0,
                "aggDiff": 0
            },
            "bradford vets (b)": {
                "games": 16,
                "wins": 8,
                "aggDiff": -6
            },
            "bradford saturday": {
                "games": 0,
                "wins": 0,
                "aggDiff": 0
            },
            "bradford saturday (b)": {
                "games": 0,
                "wins": 0,
                "aggDiff": 0
            },
            "bradford saturday (c)": {
                "games": 17,
                "wins": 10,
                "aggDiff": 33
            }
        },
        "paul bowes": {
            "totalAgg": 243,
            "totalAggAgainst": 290,
            "availableAgg": 315,
            "availablePairsAgg": 0,
            "availableHomeAgg": 168,
            "availableAwayAgg": 147,
            "availablePairsHomeAgg": 0,
            "availablePairsAwayAgg": 0,
            "totalPairsAgg": 0,
            "totalPairsAggAgainst": 0,
            "totalHomeAgg": 130,
            "totalHomeAggAgainst": 158,
            "totalPairsHomeAgg": 0,
            "totalPairsHomeAggAgainst": 0,
            "totalAwayAgg": 113,
            "totalAwayAggAgainst": 132,
            "totalPairsAwayAgg": 0,
            "totalPairsAwayAggAgainst": 0,
            "homeWins": 3,
            "homeLosses": 5,
            "awayWins": 2,
            "awayLosses": 5,
            "cupWins": 0,
            "cupLosses": 0,
            "pairWins": 0,
            "pairLosses": 0,
            "pairHomeWins": 0,
            "pairHomeLosses": 0,
            "pairAwayWins": 0,
            "pairAwayLosses": 0,
            "pairCupWins": 0,
            "pairCupLosses": 0,
            "totalGamesPlayed": 15,
            "results": [
                "paul bowes 21 - 17 kim ramsden",
                "paul bowes 21 - 10 josh mordue (a)",
                "paul bowes 19 - 21 graham roberts",
                "paul bowes 1 - 21 james davison (a)",
                "paul bowes 18 - 21 andrew heenan",
                "paul bowes 18 - 21 mark cuningham",
                "paul bowes 19 - 21 mick angus (b)",
                "paul bowes 9 - 21 peter wilcox",
                "paul bowes 21 - 19 john armitage",
                "paul bowes 20 - 21 danny towning (a)",
                "paul bowes 21 - 17 steve foster (a)",
                "paul bowes 21 - 17 andy gilroy",
                "paul bowes 19 - 21 david hoskins",
                "paul bowes 5 - 21 clive foord",
                "paul bowes 10 - 21 daniel metcalfe"
            ],
            "airewharfe monday": {
                "games": 0,
                "wins": 0,
                "aggDiff": 0
            },
            "airewharfe monday (b)": {
                "games": 0,
                "wins": 0,
                "aggDiff": 0
            },
            "mirfield": {
                "games": 0,
                "wins": 0,
                "aggDiff": 0
            },
            "mirfield (b)": {
                "games": 0,
                "wins": 0,
                "aggDiff": 0
            },
            "bradford vets": {
                "games": 0,
                "wins": 0,
                "aggDiff": 0
            },
            "bradford vets (b)": {
                "games": 0,
                "wins": 0,
                "aggDiff": 0
            },
            "bradford saturday": {
                "games": 15,
                "wins": 5,
                "aggDiff": -47
            },
            "bradford saturday (b)": {
                "games": 0,
                "wins": 0,
                "aggDiff": 0
            },
            "bradford saturday (c)": {
                "games": 0,
                "wins": 0,
                "aggDiff": 0
            }
        },
        "richard hodgson": {
            "totalAgg": 246,
            "totalAggAgainst": 189,
            "availableAgg": 273,
            "availablePairsAgg": 0,
            "availableHomeAgg": 147,
            "availableAwayAgg": 126,
            "availablePairsHomeAgg": 0,
            "availablePairsAwayAgg": 0,
            "totalPairsAgg": 0,
            "totalPairsAggAgainst": 0,
            "totalHomeAgg": 147,
            "totalHomeAggAgainst": 86,
            "totalPairsHomeAgg": 0,
            "totalPairsHomeAggAgainst": 0,
            "totalAwayAgg": 99,
            "totalAwayAggAgainst": 103,
            "totalPairsAwayAgg": 0,
            "totalPairsAwayAggAgainst": 0,
            "homeWins": 7,
            "homeLosses": 0,
            "awayWins": 2,
            "awayLosses": 4,
            "cupWins": 0,
            "cupLosses": 0,
            "pairWins": 0,
            "pairLosses": 0,
            "pairHomeWins": 0,
            "pairHomeLosses": 0,
            "pairAwayWins": 0,
            "pairAwayLosses": 0,
            "pairCupWins": 0,
            "pairCupLosses": 0,
            "totalGamesPlayed": 13,
            "results": [
                "richard hodgson 21 - 11 brian teale",
                "richard hodgson 21 - 17 richard matthews",
                "richard hodgson 21 - 13 carol wright",
                "richard hodgson 19 - 21 stuart brook",
                "richard hodgson 21 - 13 alister keighley",
                "richard hodgson 21 - 10 robert hartley",
                "richard hodgson 10 - 21 chris lodge",
                "richard hodgson 21 - 18 gary whelan",
                "richard hodgson 8 - 21 steve ainley",
                "richard hodgson 21 - 2 chris sims",
                "richard hodgson 21 - 12 bill robson",
                "richard hodgson 20 - 21 jeff bolton",
                "richard hodgson 21 - 9 john thompson"
            ],
            "airewharfe monday": {
                "games": 13,
                "wins": 9,
                "aggDiff": 57
            },
            "airewharfe monday (b)": {
                "games": 0,
                "wins": 0,
                "aggDiff": 0
            },
            "mirfield": {
                "games": 0,
                "wins": 0,
                "aggDiff": 0
            },
            "mirfield (b)": {
                "games": 0,
                "wins": 0,
                "aggDiff": 0
            },
            "bradford vets": {
                "games": 0,
                "wins": 0,
                "aggDiff": 0
            },
            "bradford vets (b)": {
                "games": 0,
                "wins": 0,
                "aggDiff": 0
            },
            "bradford saturday": {
                "games": 0,
                "wins": 0,
                "aggDiff": 0
            },
            "bradford saturday (b)": {
                "games": 0,
                "wins": 0,
                "aggDiff": 0
            },
            "bradford saturday (c)": {
                "games": 0,
                "wins": 0,
                "aggDiff": 0
            }
        },
        "stewart watson": {
            "totalAgg": 404,
            "totalAggAgainst": 311,
            "availableAgg": 441,
            "availablePairsAgg": 0,
            "availableHomeAgg": 231,
            "availableAwayAgg": 210,
            "availablePairsHomeAgg": 0,
            "availablePairsAwayAgg": 0,
            "totalPairsAgg": 0,
            "totalPairsAggAgainst": 0,
            "totalHomeAgg": 231,
            "totalHomeAggAgainst": 150,
            "totalPairsHomeAgg": 0,
            "totalPairsHomeAggAgainst": 0,
            "totalAwayAgg": 173,
            "totalAwayAggAgainst": 161,
            "totalPairsAwayAgg": 0,
            "totalPairsAwayAggAgainst": 0,
            "homeWins": 11,
            "homeLosses": 0,
            "awayWins": 5,
            "awayLosses": 5,
            "cupWins": 0,
            "cupLosses": 0,
            "pairWins": 0,
            "pairLosses": 0,
            "pairHomeWins": 0,
            "pairHomeLosses": 0,
            "pairAwayWins": 0,
            "pairAwayLosses": 0,
            "pairCupWins": 0,
            "pairCupLosses": 0,
            "totalGamesPlayed": 21,
            "results": [
                "stewart watson 21 - 12 shirley biancardo",
                "stewart watson 9 - 21 gordon longfellow",
                "stewart watson 21 - 14 ian fickling",
                "stewart watson 21 - 5 andy smith",
                "stewart watson 21 - 11 steve birch",
                "stewart watson 21 - 8 brian wardle",
                "stewart watson 21 - 13 alan broadwell",
                "stewart watson 21 - 17 jeff bolton",
                "stewart watson 19 - 21 john benson",
                "stewart watson 21 - 13 pat appleyard",
                "stewart watson 21 - 20 carol matthews",
                "stewart watson 18 - 21 janice waite",
                "stewart watson 21 - 16 andy smith",
                "stewart watson 21 - 13 steven senior",
                "stewart watson 21 - 10 diane done",
                "stewart watson 14 - 21 ken bull",
                "stewart watson 21 - 16 john benson",
                "stewart watson 21 - 12 alan clements",
                "stewart watson 8 - 21 ian matthews",
                "stewart watson 21 - 17 graham oliver",
                "stewart watson 21 - 9 ken walker"
            ],
            "airewharfe monday": {
                "games": 17,
                "wins": 13,
                "aggDiff": 81
            },
            "airewharfe monday (b)": {
                "games": 0,
                "wins": 0,
                "aggDiff": 0
            },
            "mirfield": {
                "games": 0,
                "wins": 0,
                "aggDiff": 0
            },
            "mirfield (b)": {
                "games": 0,
                "wins": 0,
                "aggDiff": 0
            },
            "bradford vets": {
                "games": 4,
                "wins": 3,
                "aggDiff": 12
            },
            "bradford vets (b)": {
                "games": 0,
                "wins": 0,
                "aggDiff": 0
            },
            "bradford saturday": {
                "games": 0,
                "wins": 0,
                "aggDiff": 0
            },
            "bradford saturday (b)": {
                "games": 0,
                "wins": 0,
                "aggDiff": 0
            },
            "bradford saturday (c)": {
                "games": 0,
                "wins": 0,
                "aggDiff": 0
            }
        }
    },
    "teamResults": [],
    "lastUpdated": "06/12/2024",
    "statsYear": "2013"
}